MANIFEST.in
README
setup.py
ikeys_cli/__init__.py
ikeys_cli.egg-info/PKG-INFO
ikeys_cli.egg-info/SOURCES.txt
ikeys_cli.egg-info/dependency_links.txt
ikeys_cli.egg-info/pbr.json
ikeys_cli.egg-info/requires.txt
ikeys_cli.egg-info/top_level.txt